test/__init__.py
test/conftest.py
test/integration/__init__.py
test/integration/conftest.py
test/integration/test_api_game_data.py
test/integration/test_api_league_data.py
test/integration/test_api_player_data.py
test/integration/test_api_team_data.py
test/integration/test_api_user_data.py
yfpy/__init__.py
yfpy/data.py
yfpy/exceptions.py
yfpy/logger.py
yfpy/models.py
yfpy/query.py
yfpy/utils.py
yfpy-16.0.3.dist-info/LICENSE
yfpy-16.0.3.dist-info/METADATA
yfpy-16.0.3.dist-info/WHEEL
yfpy-16.0.3.dist-info/top_level.txt
yfpy-16.0.3.dist-info/RECORD
