Metadata-Version: 2.1
Name: yfpy
Version: 16.0.3
Summary: Python API wrapper for the Yahoo Fantasy Sports public API.
Home-page: https://github.com/uberfastman/yfpy
Download-URL: https://github.com/uberfastman/yfpy/archive/v16.0.3.tar.gz
Author: Wren J. R.
Author-email: uberfastman@uberfastman.dev
Keywords: yahoo fantasy sports api wrapper nfl football nhl hockey mlb baseball nba basketball
Classifier: Programming Language :: Python :: 3
Classifier: Programming Language :: Python :: 3.10
Classifier: Programming Language :: Python :: 3.11
Classifier: Programming Language :: Python :: 3.12
Classifier: License :: OSI Approved :: GNU General Public License v3 (GPLv3)
Classifier: Operating System :: OS Independent
Classifier: Development Status :: 5 - Production/Stable
Classifier: Topic :: Software Development :: Libraries :: Python Modules
Classifier: Environment :: Console
Classifier: Intended Audience :: Developers
Requires-Python: >=3.10
License-File: LICENSE
Requires-Dist: bandit==1.7.9
Requires-Dist: coverage==7.6.1
Requires-Dist: flake8==7.1.1
Requires-Dist: pytest==8.3.3
Requires-Dist: python-dotenv==1.0.1
Requires-Dist: requests==2.32.3
Requires-Dist: ruamel.yaml==0.18.6
Requires-Dist: stringcase==1.2.0
Requires-Dist: yahoo-oauth==2.1.0
